{"type":"lesson","title":{"rus":"Маменькин сынок","eng":"A mama’s boy","start":710,"end":2023},"audio":"139.mp3","sentences":[{"eng":"– Take off your coat and boots,","rus":"– [Сними|снимать (одежду)|to take off] [пальто|пальто, шуба|a coat] и [ботинки|ботинки|boots],","start":3100,"end":5342},{"eng":"put your hat on the shelf,","rus":"[положи|класть|to put] [шапку|шапка; шляпа|a hat] на [полку|полка|a shelf],","start":6210,"end":8239},{"eng":"wash your hands","rus":"[помой|мыть|to wash] [руки|рука|a hand]","start":9140,"end":10519},{"eng":"and sit down at the table.","rus":"и [садись|сидеть|to sit] к [столу|стол|a table].","start":10720,"end":12529},{"eng":"Don’t play with the knife,","rus":"Не играй с [ножом|нож|a knife],","start":13230,"end":15069},{"eng":"don’t oversalt your soup,","rus":"не [пересаливай|пересаливать, пересолить|to oversalt] [суп|суп|soup],","start":15970,"end":17899},{"eng":"don’t make faces, straighten up!","rus":"не [гримасничай|гримасничать|to make faces], [выпрямись|выпрямляться|to straighten (up)]!","start":18820,"end":22219},{"eng":"Take fresh bread,","rus":"[Возьми|брать|to take] [свежий|свежий|fresh] [хлеб|хлеб|bread],","start":23320,"end":24789},{"eng":"don’t eat chips,","rus":"не [ешь|есть, кушать|to eat] [чипсы|чипсы|chips],","start":25390,"end":26959},{"eng":"don’t knock the table,","rus":"не [стучи|стучать|to knock] по [столу|стол|a table],","start":27560,"end":29379},{"eng":"don't look through the window!","rus":"не [смотри|смотреть, выглядеть|to look] в [окно|окно|a window]!","start":30380,"end":32439},{"eng":"Calm down!","rus":"Успокойся!","start":33240,"end":34619},{"eng":"Don't eat pasta with your fingers!","rus":"Не [ешь|есть, кушать|to eat] [макароны|макароны|pasta] [пальцами|палец|a finger]!","start":35520,"end":38359},{"eng":"Use a fork!","rus":"[Пользуйся|использовать|to use] [вилкой|вилка|a fork]!","start":39071,"end":40349},{"eng":"Do you want some more pasta?","rus":"[Хочешь|хотеть|to want] добавку [макарон|макароны|pasta]?","start":41450,"end":43619},{"eng":"Put remote back!","rus":"[Положи|класть|to put] [пульт|дистанционный пульт|a remote] от [телевизора|телевизор|a TV-set] на [место|место|a place]!","start":44520,"end":46379},{"eng":"Don’t watch your foolish football match at lunch-time!","rus":"Не смотри свой [дурацкий|дурацкий; глупый|foolish] [футбол|футбол|football] во [время обеда|время обеда|lunch-time]!","start":47520,"end":51509},{"eng":"Don’t be naughty and eat up your meatballs!","rus":"Не [капризничай|капризничать, озорничать|to be naughty] и [доешь|доедать|to eat up] [фрикадельки|фрикадельки; тефтели|meatballs]!","start":52610,"end":56219},{"eng":"And now be polite and say","rus":"А теперь будь [вежливым|вежливый(ая)|polite] и [скажи|говорить; сказать|to say]:","start":56820,"end":60129},{"eng":"«Thank you so much!»","rus":"«Большое [спасибо|спасибо|Thank you]».","breakAfter":true,"start":60530,"end":62159},{"eng":"– Mummy!","rus":"– [Мама|мама|Mum; Mummy]!!!","start":63760,"end":64589},{"eng":"I am 37 years old!","rus":"Мне 37 лет!","start":64690,"end":67179},{"eng":"I am a famous scientist!","rus":"Я [известный|известный(ая)|famous] [учёный|учёный|a scientist]!","start":67380,"end":69379},{"eng":"I lead a huge company!","rus":"Я [руковожу|руководить|to lead] [огромной|огромный|huge] [компанией|компания|a company].","start":69720,"end":71579},{"eng":"I am a respectable person!","rus":"Я [уважаемый|уважаемый|respectable] [человек|человек, лицо, личность|a person]!","breakAfter":true,"start":72080,"end":74199},{"eng":"– I don't understand anything!","rus":"– Я ничего не [понимаю|понимать|to understand]!","start":75400,"end":77869},{"eng":"I always speak to you like this","rus":"Я [всегда|всегда|always] так с тобой [разговариваю|говорить, разговаривать|to speak],","start":78870,"end":81219},{"eng":"and you never react this way…","rus":"и ты [никогда|никогда|never] так не [реагируешь|реагировать|to react]…","breakAfter":true,"start":81820,"end":83949},{"eng":"– Don’t worry, Mummy.","rus":"– [Не волнуйся|не волнуйся|don't worry], [мамочка|мамочка, мамуля|Mummy]!","start":85450,"end":87099},{"eng":"Thank you so much!","rus":"Большое [спасибо|спасибо|Thank you].","breakAfter":true,"start":87220,"end":88599},{"eng":"– You are welcome!","rus":"– [На здоровье|На здоровье|You are welcome].","start":89710,"end":91230}],"image":"//classroom.kespa.ru/cdn/images/1x/texts/139.jpg","image2x":"//classroom.kespa.ru/cdn/images/2x/texts/139.jpg","audioPath":"//classroom.kespa.ru/cdn/audio/texts/139.mp3","cdnPath":"//classroom.kespa.ru/cdn/audio/texts/","id":139}